depocs/__init__.py
depocs-2.1.0.dist-info/METADATA
depocs-2.1.0.dist-info/WHEEL
depocs-2.1.0.dist-info/RECORD
