Metadata-Version: 2.1
Name: depocs
Version: 2.1.0
Summary: Scoped thread-local mixin class
Home-page: https://github.com/sdelements/depocs
License: MIT
Author: Security Compass
Author-email: contact@securitycompass.com
Requires-Python: >=3.12,<3.13
Classifier: Development Status :: 4 - Beta
Classifier: Intended Audience :: Developers
Classifier: License :: OSI Approved :: MIT License
Classifier: Natural Language :: English
Classifier: Programming Language :: Python :: 3
Classifier: Programming Language :: Python :: 3.12
Classifier: Topic :: Software Development :: Libraries :: Python Modules
